marmee/__init__.py
marmee/abstract_marmee.py
marmee/marmee.py
marmee/model/__init__.py
marmee/model/base.py
marmee/model/filter.py
marmee/model/input.py
marmee/model/output.py
marmee/model/rule.py
marmee/utils/__init__.py
marmee/utils/helpers.py
marmee/utils/parser.py
marmee-0.2.4.dist-info/METADATA
marmee-0.2.4.dist-info/RECORD
marmee-0.2.4.dist-info/WHEEL
marmee-0.2.4.dist-info/top_level.txt
