Metadata-Version: 2.1
Name: marmee
Version: 0.2.4
Summary: Execute safely Google Earth Engine algorithm througha tunnel like a marmot
Home-page: https://github.com/francbartoli/marmee
Author: Francesco Bartoli
Author-email: francesco.bartoli@geobeyond.it
License: MIT license
Keywords: marmee
Platform: UNKNOWN
Classifier: Development Status :: 2 - Pre-Alpha
Classifier: Intended Audience :: Developers
Classifier: License :: OSI Approved :: MIT License
Classifier: Natural Language :: English
Classifier: Programming Language :: Python :: 2
Classifier: Programming Language :: Python :: 2.7
Classifier: Programming Language :: Python :: 3
Classifier: Programming Language :: Python :: 3.4
Classifier: Programming Language :: Python :: 3.5
Classifier: Programming Language :: Python :: 3.6
Requires-Dist: pendulum
Requires-Dist: earthengine-api
Requires-Dist: marshmallow (>=3.0.0b12)
Requires-Dist: marshmallow-oneofschema (>=2.0.0b1)
Requires-Dist: py-stac
